todo/__init__.py
todo/manager.py
todomanager-0.0.2.dist-info/METADATA
todomanager-0.0.2.dist-info/WHEEL
todomanager-0.0.2.dist-info/entry_points.txt
todomanager-0.0.2.dist-info/top_level.txt
todomanager-0.0.2.dist-info/RECORD
