Metadata-Version: 2.1
Name: todomanager
Version: 0.0.2
Summary: Manage your daily tasks in the terminal with the super readable command-line interface design
Author-email: Alex Zolotarov <alex@zolotarov.me>
Requires-Python: >=3.9
Requires-Dist: pyyaml
Requires-Dist: rich
Requires-Dist: fire
